smev3Transform/__init__.py
smev3Transform/test_smev_transform.py
smev3Transform/transform.py
smev3Transform-1.0.dist-info/LICENSE
smev3Transform-1.0.dist-info/METADATA
smev3Transform-1.0.dist-info/WHEEL
smev3Transform-1.0.dist-info/top_level.txt
smev3Transform-1.0.dist-info/RECORD
