Metadata-Version: 2.1
Name: smev3Transform
Version: 1.0
Summary: Пакет канонизации и нормализации xml элемента для подписания в СМЭВ 3.
Home-page: https://github.com/Tartorus/smev3Transform
Author: Basharov Iliyas Ildarovich
Author-email: 5q00@mail.com
License: UNKNOWN
Platform: UNKNOWN
Classifier: Programming Language :: Python :: 3
Classifier: License :: OSI Approved :: MIT License
Classifier: Operating System :: OS Independent
Requires-Dist: lxml
